{
    "username": "aespa_official",
    "profile_url": "https://www.instagram.com/aespa_official/",
    "followers": "13.2M",
    "following": "6",
    "number_of_posts": "2,373",
    "posts_info": [
        {
            "url": "https://www.instagram.com/aespa_official/reel/C4IbyffL8wx/",
            "urlImage": "https://scontent-bom1-2.cdninstagram.com/v/t51.29350-15/431580256_1071608260774028_1574003227559072679_n.jpg?stp=c0.280.720.720a_dst-jpg_e15_s640x640&_nc_ht=scontent-bom1-2.cdninstagram.com&_nc_cat=108&_nc_ohc=6BdKiioaBigAX9bf50Z&edm=AOQ1c0wBAAAA&ccb=7-5&oh=00_AfC2dflfaQXewygRYDzxd1Fxeczss3lKYQSD_vMmUEn3Lg&oe=65EB3394&_nc_sid=8b3546",
            "description": "\ud83e\udd2f \n\n#aespa #\uc5d0\uc2a4\ud30c \n#NINGNING #\ub2dd\ub2dd @imnotningning",
            "mentions": [
                "@imnotningning"
            ],
            "likes": "462,115"
        },
        {
            "url": "https://www.instagram.com/aespa_official/p/C4E26HAP1_O/",
            "urlImage": "https://scontent-bom2-2.cdninstagram.com/v/t51.29350-15/431046602_1873869223064502_5614842179273740648_n.jpg?stp=dst-jpg_e35_p1080x1080&_nc_ht=scontent-bom2-2.cdninstagram.com&_nc_cat=1&_nc_ohc=uOYr9-iG96IAX8eimCc&edm=AOQ1c0wBAAAA&ccb=7-5&oh=00_AfCVrPA0fZQ2c6VTqHVIEZ0A1GVaUovq9OEr6fq6pBQnpQ&oe=65EF0609&_nc_sid=8b3546",
            "description": "Photo by aespa \u110b\u1166\u1109\u1173\u1111\u1161 on March 03, 2024. May be an image of 1 person, leather and purse.",
            "mentions": [],
            "likes": "452,669"
        },
        {
            "url": "https://www.instagram.com/aespa_official/reel/C4DSJ9jLY9L/",
            "urlImage": "https://scontent-bom2-2.cdninstagram.com/v/t51.29350-15/431571734_926767009173706_4634173916888327279_n.jpg?stp=c0.187.480.480a_dst-jpg_e15&_nc_ht=scontent-bom2-2.cdninstagram.com&_nc_cat=1&_nc_ohc=mp4wHG0rFXEAX-jtDYH&edm=AOQ1c0wBAAAA&ccb=7-5&oh=00_AfAaT_yktfbkqy388R2jtvoMpeo4jCyEFu8534r2woyMog&oe=65EB3F2E&_nc_sid=8b3546",
            "description": "\ud83d\ude0f\ud83d\udc46\n\n#aespa #\uc5d0\uc2a4\ud30c \n#GISELLE #\uc9c0\uc824 @aerichandesu",
            "mentions": [
                "@aerichandesu"
            ],
            "likes": "488,016"
        },
        {
            "url": "https://www.instagram.com/aespa_official/p/C3-qjcGPuyT/",
            "urlImage": "https://scontent-bom2-2.cdninstagram.com/v/t51.29350-15/430494268_965337111609070_8780859740821661501_n.jpg?stp=dst-jpg_e35_p1080x1080&_nc_ht=scontent-bom2-2.cdninstagram.com&_nc_cat=1&_nc_ohc=cQz4bqL5yXMAX8s6Oqg&edm=AOQ1c0wBAAAA&ccb=7-5&oh=00_AfD9oh9xRkELT6plRDDfTL-VSqnr0CqTqMvHznd4kEx9sQ&oe=65EE3C49&_nc_sid=8b3546",
            "description": "Photo by aespa \u110b\u1166\u1109\u1173\u1111\u1161 on March 01, 2024. May be an image of 1 person, coat, purse and miniskirt.",
            "mentions": [],
            "likes": "800,626"
        },
        {
            "url": "https://www.instagram.com/aespa_official/reel/C3-IugJP7QJ/",
            "urlImage": "https://scontent-bom2-2.cdninstagram.com/v/t51.29350-15/430471661_908914027442413_2507194594506557629_n.jpg?stp=c0.280.720.720a_dst-jpg_e15_s640x640&_nc_ht=scontent-bom2-2.cdninstagram.com&_nc_cat=1&_nc_ohc=75oXrrUQhAsAX_3VGq6&edm=AOQ1c0wBAAAA&ccb=7-5&oh=00_AfBbGKKa7CpvoetvFLcaonasm4ObESX2O9gxL9WUNXvH9Q&oe=65EACDA1&_nc_sid=8b3546",
            "description": "\u0b67\u0f3c\u25d5 \u1d25 \u25d5 \ud83c\udf80 \u0f3d\u0b68 \n\n#\uae40\ubf40\uc090\n#aespa #\uc5d0\uc2a4\ud30c \n#WINTER #\uc708\ud130 @imwinter",
            "mentions": [
                "@imwinter"
            ],
            "likes": "899,667"
        },
        {
            "url": "https://www.instagram.com/aespa_official/p/C39Ziosrhud/",
            "urlImage": "https://scontent-bom1-1.cdninstagram.com/v/t51.29350-15/430413542_1495580754717935_3817982673124885878_n.jpg?stp=dst-jpg_e35_p1080x1080&_nc_ht=scontent-bom1-1.cdninstagram.com&_nc_cat=111&_nc_ohc=Bum4a6jajJEAX-rEVSt&edm=AOQ1c0wBAAAA&ccb=7-5&oh=00_AfA2EeMdPrH7O5Hny5ltfoabzJHWTMdL7gl925L_eOPayg&oe=65EE1B68&_nc_sid=8b3546",
            "description": "Photo by aespa \u110b\u1166\u1109\u1173\u1111\u1161 on February 29, 2024. May be an image of 1 person, braids, makeup and dress.",
            "mentions": [],
            "likes": "744,782"
        },
        {
            "url": "https://www.instagram.com/aespa_official/reel/C37j1tBv-Ug/",
            "urlImage": "https://scontent-bom1-1.cdninstagram.com/v/t51.29350-15/430803909_1481425169466018_6974946389881437962_n.jpg?stp=c0.280.720.720a_dst-jpg_e15_s640x640&_nc_ht=scontent-bom1-1.cdninstagram.com&_nc_cat=106&_nc_ohc=MFcf7J_XvC8AX8r_BkS&edm=AOQ1c0wBAAAA&ccb=7-5&oh=00_AfCNIKADtNhaWSIMpnyV0-ofT08Fomp2HpHeb-_L08_yIg&oe=65EB01B5&_nc_sid=8b3546",
            "description": "who u foolin\n\n#aespa #\uc5d0\uc2a4\ud30c \n#GISELLE #\uc9c0\uc824 @aerichandesu \n#NINGNING #\ub2dd\ub2dd @imnotningning",
            "mentions": [
                "@aerichandesu",
                "@imnotningning"
            ],
            "likes": "1,064,077"
        },
        {
            "url": "https://www.instagram.com/aespa_official/reel/C34_FS-ry0Z/",
            "urlImage": "https://scontent-bom2-2.cdninstagram.com/v/t51.29350-15/429907728_908917897599714_3264149496917387636_n.jpg?stp=c0.280.720.720a_dst-jpg_e15_s640x640&_nc_ht=scontent-bom2-2.cdninstagram.com&_nc_cat=1&_nc_ohc=xyLOVFPrSsMAX8sOJkE&edm=AOQ1c0wBAAAA&ccb=7-5&oh=00_AfAzuPaXWnaFYAiatnM7-yvXMchOws73y3VLfks2rCBLMA&oe=65EAD925&_nc_sid=8b3546",
            "description": "LOOK AT ME \ud83d\udc98 \n\n#aespa #\uc5d0\uc2a4\ud30c \n#WINTER #\uc708\ud130 @imwinter",
            "mentions": [
                "@imwinter"
            ],
            "likes": "2,093,523"
        },
        {
            "url": "https://www.instagram.com/aespa_official/p/C30EZ98PfJ9/",
            "urlImage": "https://scontent-bom2-2.cdninstagram.com/v/t51.29350-15/429894555_389938793788450_8743806253064633662_n.jpg?stp=c0.180.1440.1440a_dst-jpg_e35_s640x640_sh0.08&_nc_ht=scontent-bom2-2.cdninstagram.com&_nc_cat=1&_nc_ohc=B8Y6ixfT2tEAX87ucm4&edm=AOQ1c0wBAAAA&ccb=7-5&oh=00_AfCR10zevyd9rdO9kjc2f7cN6y0oj5ZnZ269a-XzKDsUCw&oe=65EE2DCB&_nc_sid=8b3546",
            "description": "Photo by aespa \u110b\u1166\u1109\u1173\u1111\u1161 on February 26, 2024. May be an image of 2 people and text.",
            "mentions": [],
            "likes": "538,810"
        },
        {
            "url": "https://www.instagram.com/aespa_official/reel/C30DVAdPyS1/",
            "urlImage": "https://scontent-bom1-2.cdninstagram.com/v/t51.29350-15/429723695_806762184621972_7945794737236670381_n.jpg?stp=c0.280.720.720a_dst-jpg_e15_s640x640&_nc_ht=scontent-bom1-2.cdninstagram.com&_nc_cat=100&_nc_ohc=0XNGeFXPW4UAX80aA9-&edm=AOQ1c0wBAAAA&ccb=7-5&oh=00_AfCI_2q0Qb5uaQ9v-W6iRglu4O92DPIOsgURZ1cdcXvimA&oe=65EAC42A&_nc_sid=8b3546",
            "description": "\ud83d\udc46\ud83e\udee5\ud83d\udc46\n\n#SMTOWN #ONE_PRODUCTION \n#GirlsGeneration #\uc18c\ub140\uc2dc\ub300 @girlsgeneration\n#HYOYEON #\ud6a8\uc5f0 @hyoyeon_x_x\n#aespa #\uc5d0\uc2a4\ud30c #\uc544\uae30\uc18c\uc6d0 \n#KARINA #\uce74\ub9ac\ub098 @katarinabluu",
            "mentions": [
                "@girlsgeneration",
                "@hyoyeon_x_x",
                "@katarinabluu"
            ],
            "likes": "872,548"
        },
        {
            "url": "https://www.instagram.com/aespa_official/reel/C30DNPVvS-0/",
            "urlImage": "https://scontent-bom2-2.cdninstagram.com/v/t51.29350-15/429841386_725477236376301_1336430883430786349_n.jpg?stp=c0.280.720.720a_dst-jpg_e15_s640x640&_nc_ht=scontent-bom2-2.cdninstagram.com&_nc_cat=1&_nc_ohc=MRtS8cck0Z4AX-IcVbe&edm=AOQ1c0wBAAAA&ccb=7-5&oh=00_AfCG0Tt18ALUqFyz9qtLc_JKY0qtVY9_TaP4GO8prjnapw&oe=65EAF30B&_nc_sid=8b3546",
            "description": "#HYO unnie in my pants \ud83d\ude02 \n\n#SMTOWN #ONE_PRODUCTION \n#GirlsGeneration #\uc18c\ub140\uc2dc\ub300 @girlsgeneration\n#HYOYEON #\ud6a8\uc5f0 @hyoyeon_x_x\n#aespa #\uc5d0\uc2a4\ud30c #WINTER #\uc708\ud130 @imwinter",
            "mentions": [
                "@girlsgeneration",
                "@hyoyeon_x_x",
                "@imwinter"
            ],
            "likes": "1,468,232"
        },
        {
            "url": "https://www.instagram.com/aespa_official/reel/C3z1RdarMjf/",
            "urlImage": "https://scontent-bom1-2.cdninstagram.com/v/t51.29350-15/429916140_7242763512451437_1268640244074761428_n.jpg?stp=c0.280.720.720a_dst-jpg_e15_s640x640&_nc_ht=scontent-bom1-2.cdninstagram.com&_nc_cat=109&_nc_ohc=wVM6tHDPRH8AX_k5qTA&edm=AOQ1c0wBAAAA&ccb=7-5&oh=00_AfDnEiPAgx6QoCiGGZx-l3up_5bvy6ysD8xpzxtB5ZT31A&oe=65EB3F6C&_nc_sid=8b3546",
            "description": "\ud83d\udc2f\ud83e\ude77 \n\n#aespa #\uc5d0\uc2a4\ud30c \n#NINGNING #\ub2dd\ub2dd @imnotningning",
            "mentions": [
                "@imnotningning"
            ],
            "likes": "1,316,651"
        }
    ]
}