{
    "username": "ddlovato",
    "profile_url": "https://www.instagram.com/ddlovato/",
    "followers": "157M",
    "following": "835",
    "number_of_posts": "160",
    "posts_info": [
        {
            "url": "https://www.instagram.com/p/C31ANZrSNmW/",
            "urlImage": "https://scontent.cdninstagram.com/v/t51.29350-15/429786369_359878206955625_4693384652109031238_n.jpg?stp=dst-jpg_e35&efg=eyJ2ZW5jb2RlX3RhZyI6ImltYWdlX3VybGdlbi45NjB4NjQwLnNkciJ9&_nc_ht=scontent.cdninstagram.com&_nc_cat=105&_nc_ohc=btnR1n2aqd8AX8ln5pn&edm=APs17CUBAAAA&ccb=7-5&ig_cache_key=MzMxMTU1NDAxNzUxOTc4NTUxNg%3D%3D.2-ccb7-5&oh=00_AfDYadOR00m7U9kVKT7f4eNqy1z-YFS4K8csP9SzGpWDeg&oe=65EB98FF&_nc_sid=10d13b",
            "description": "\ud83d\ude18",
            "mentions": [],
            "likes": "370,347"
        },
        {
            "url": "https://www.instagram.com/p/C3l1MU-RHZ3/",
            "urlImage": "https://scontent.cdninstagram.com/v/t51.29350-15/429013784_777176503786301_6555237055293137098_n.jpg?stp=dst-jpg_e35&efg=eyJ2ZW5jb2RlX3RhZyI6ImltYWdlX3VybGdlbi4xNDQweDE4MDAuc2RyIn0&_nc_ht=scontent.cdninstagram.com&_nc_cat=105&_nc_ohc=hi7ZC0LNPlMAX-JNK_5&edm=APs17CUBAAAA&ccb=7-5&ig_cache_key=MzMwNzI4MzQzOTgzMjg0MzkwMg%3D%3D.2-ccb7-5&oh=00_AfALH3V3xZEl6K53c1Jdug7itr3cKCcIPCQ-BcZ1HNyNKw&oe=65EBDFEE&_nc_sid=10d13b",
            "description": "If you didn\u2019t make shirts to go to the Olive Garden, did you even go?",
            "mentions": [],
            "likes": "320,076"
        },
        {
            "url": "https://www.instagram.com/reel/C3V6hlFOJls/",
            "urlImage": "https://scontent.cdninstagram.com/v/t51.29350-15/427430727_1363277831053082_2670812923195645074_n.jpg?stp=dst-jpg_e15&efg=eyJ2ZW5jb2RlX3RhZyI6ImltYWdlX3VybGdlbi4xMDgweDE5MjAuc2RyIn0&_nc_ht=scontent.cdninstagram.com&_nc_cat=102&_nc_ohc=DF13mbX3elEAX9lp7vf&edm=APs17CUBAAAA&ccb=7-5&ig_cache_key=MzMwMjgwMzI5NjAwMjU0NjAyOA%3D%3D.2-ccb7-5&oh=00_AfBdfLVhmDnEd0FzPICSln3OrS8AF2ziYYxv2CdNZ0ke_w&oe=65E9BB8E&_nc_sid=10d13b",
            "description": "Nothing says love like a bouquet of pickles \u2764\ufe0f",
            "mentions": [],
            "likes": "41,230"
        },
        {
            "url": "https://www.instagram.com/p/C3VouU6vQVf/",
            "urlImage": "https://scontent.cdninstagram.com/v/t51.29350-15/427221946_752496566967061_4343322924494932226_n.jpg?stp=dst-jpg_e35&efg=eyJ2ZW5jb2RlX3RhZyI6ImltYWdlX3VybGdlbi4xMjc5eDEyODguc2RyIn0&_nc_ht=scontent.cdninstagram.com&_nc_cat=101&_nc_ohc=8evE4V048xYAX--3r3x&edm=APs17CUBAAAA&ccb=7-5&ig_cache_key=MzMwMjcyNTAwMTc2OTEwODU2MA%3D%3D.2-ccb7-5&oh=00_AfCqsAa4bqVCsI-1MbDXYFrkNGH5ZflmZIAKjoJwTqRJgg&oe=65EB406A&_nc_sid=10d13b",
            "description": "Where do I even begin.. I\u2019m so beyond grateful to call you my fianc\u00e9 because every day since you walked into my life has been a dream. I laugh harder and more often and smile a million times more than I ever have in my life.. I truly never knew a love like this could exist.. but YOU - you are loving, caring, compassionate, gorgeous, fucking hilarious, so talented and so kind to everyone you meet.. I\u2019m beyond lucky to call you mine.. thank you for giving me the best two years of my life so far.. and here\u2019s to many more Valentines together baby. I love you \ud83e\udd79\ud83d\udda4",
            "mentions": [],
            "likes": "511,661"
        },
        {
            "url": "https://www.instagram.com/p/C3ThKGWPcz1/",
            "urlImage": "https://scontent.cdninstagram.com/v/t51.29350-15/426699755_24791499790497529_3516287895148651497_n.jpg?stp=dst-jpg_e35&efg=eyJ2ZW5jb2RlX3RhZyI6ImltYWdlX3VybGdlbi4xNDQweDE4MDAuc2RyIn0&_nc_ht=scontent.cdninstagram.com&_nc_cat=101&_nc_ohc=rHg31fACgN8AX_fGrVf&edm=APs17CUBAAAA&ccb=7-5&ig_cache_key=MzMwMjEyODc3NzA5MzE5MjE0NQ%3D%3D.2-ccb7-5&oh=00_AfCxKl7gbPUowoSydIaBpN-4nIjNuTNsUn_WkWEebRcBzQ&oe=65EC7D93&_nc_sid=10d13b",
            "description": "Fried pickle dip anyone?\ud83e\udd0c\ud83c\udffc",
            "mentions": [],
            "likes": "286,062"
        },
        {
            "url": "https://www.instagram.com/p/C3Dlb-gvWS3/",
            "urlImage": "https://scontent.cdninstagram.com/v/t51.29350-15/425601026_1090139272129435_4867282405540374545_n.jpg?stp=dst-jpg_e35&efg=eyJ2ZW5jb2RlX3RhZyI6ImltYWdlX3VybGdlbi4xNDQweDE3OTUuc2RyIn0&_nc_ht=scontent.cdninstagram.com&_nc_cat=107&_nc_ohc=lrJU8gGrvXYAX83avoF&edm=APs17CUBAAAA&ccb=7-5&ig_cache_key=MzI5NzY0Mzk5OTgzMjg3OTIzMw%3D%3D.2-ccb7-5&oh=00_AfBGY20UmOXIrMHz2YFjYvlmBeyusB8Ep44qaOP79pa-RQ&oe=65EC1154&_nc_sid=10d13b",
            "description": "Double B, Every Me. The choice is yours. Embrace the BOSS you were meant to be.  #beyourownBOSS",
            "mentions": [],
            "likes": "188,398"
        },
        {
            "url": "https://www.instagram.com/p/C2-mQFESbJ4/",
            "urlImage": "https://scontent.cdninstagram.com/v/t51.29350-15/425125031_1087527932493433_1251778502638562343_n.jpg?stp=dst-jpg_e35&efg=eyJ2ZW5jb2RlX3RhZyI6ImltYWdlX3VybGdlbi4xNDQweDE3MjIuc2RyIn0&_nc_ht=scontent.cdninstagram.com&_nc_cat=101&_nc_ohc=I5BdyLm2kgcAX-iwzMg&edm=APs17CUBAAAA&ccb=7-5&ig_cache_key=MzI5NjI0MDIwMjMzOTExMzg4OQ%3D%3D.2-ccb7-5&oh=00_AfAmPSuHOc4P_u_VvXGXeT3voq1biHDrkwkVI3dr3Kuomg&oe=65EAAFD0&_nc_sid=10d13b",
            "description": "This dress tho\u2026 \ud83d\udda4",
            "mentions": [],
            "likes": "452,167"
        },
        {
            "url": "https://www.instagram.com/p/C22iNpXLZHL/",
            "urlImage": "https://scontent.cdninstagram.com/v/t51.29350-15/424612587_753158023051460_431506362816568721_n.jpg?stp=dst-jpg_e35&efg=eyJ2ZW5jb2RlX3RhZyI6ImltYWdlX3VybGdlbi4xNDQweDE4MDAuc2RyIn0&_nc_ht=scontent.cdninstagram.com&_nc_cat=108&_nc_ohc=R68F28XubecAX-MZWp2&edm=APs17CUBAAAA&ccb=7-5&ig_cache_key=MzI5Mzk3MDY0NTIwNzc4ODA5Nw%3D%3D.2-ccb7-5&oh=00_AfDz3994cVuLe0pv-4YHOA2iTuUf9V10OR5gugtcHY0AIw&oe=65EAFFA9&_nc_sid=10d13b",
            "description": "@drewbarrymore is an angel on earth \ud83e\udd79\ud83d\udda4",
            "mentions": [
                "@drewbarrymore"
            ],
            "likes": "736,203"
        },
        {
            "url": "https://www.instagram.com/p/C2sbyuGrTpj/",
            "urlImage": "https://scontent.cdninstagram.com/v/t51.29350-15/423558845_2660385270785896_7142695672066621859_n.jpg?stp=dst-jpg_e35&efg=eyJ2ZW5jb2RlX3RhZyI6ImltYWdlX3VybGdlbi4xNDQweDE2NDguc2RyIn0&_nc_ht=scontent.cdninstagram.com&_nc_cat=104&_nc_ohc=LijO3HuSeeAAX_O1JAl&edm=APs17CUBAAAA&ccb=7-5&ig_cache_key=MzI5MTEyNzY1NTQ4NTQ5NTA1NQ%3D%3D.2-ccb7-5&oh=00_AfBTTtX_oFTXxldxvwOg3D1ncBTQrycDgGIMhp_oWkMucA&oe=65EC87C3&_nc_sid=10d13b",
            "description": "Uno no mercy at @craigsla >",
            "mentions": [
                "@craigsla"
            ],
            "likes": "622,590"
        },
        {
            "url": "https://www.instagram.com/p/C2Qo3I2v8as/",
            "urlImage": "https://scontent.cdninstagram.com/v/t51.29350-15/419542156_778567300758086_6263034312547299409_n.jpg?stp=dst-jpg_e35&efg=eyJ2ZW5jb2RlX3RhZyI6ImltYWdlX3VybGdlbi4xNDQweDE4MDAuc2RyIn0&_nc_ht=scontent.cdninstagram.com&_nc_cat=102&_nc_ohc=1q4AaROGIHYAX9j8Xpa&edm=APs17CUBAAAA&ccb=7-5&ig_cache_key=MzI4MzMwMzgzNTE3NDI1NDI0OQ%3D%3D.2-ccb7-5&oh=00_AfD44WQi02m3gAU479v5wCoBv-cLyBI3BC4BLJgNVVomEQ&oe=65EB758F&_nc_sid=10d13b",
            "description": "Swipe for an uncanny resemblance to a baby seal \ud83e\uddad",
            "mentions": [],
            "likes": "598,918"
        },
        {
            "url": "https://www.instagram.com/reel/C1iCki6vVbT/",
            "urlImage": "https://scontent.cdninstagram.com/v/t51.29350-15/415953184_917028103277110_7711485878265271520_n.jpg?stp=dst-jpg_e15&efg=eyJ2ZW5jb2RlX3RhZyI6ImltYWdlX3VybGdlbi43MjB4MTI4MC5zZHIifQ&_nc_ht=scontent.cdninstagram.com&_nc_cat=110&_nc_ohc=UelN0hib9TkAX9NMILG&edm=APs17CUBAAAA&ccb=7-5&ig_cache_key=MzI3MDE4NzU4NjkxMTI5NTE4Nw%3D%3D.2-ccb7-5&oh=00_AfA_IM5UF-QJY5dpIsRmMwxitaabXhlAdo4eTQ9oSuTsNw&oe=65E9AA4C&_nc_sid=10d13b",
            "description": "2023 \ud83e\udd79\ud83d\udda4 happy new year!",
            "mentions": [],
            "likes": "155,807"
        },
        {
            "url": "https://www.instagram.com/p/C1U-AqkP8uK/",
            "urlImage": "https://scontent.cdninstagram.com/v/t51.29350-15/412566681_674640991504617_2075407521039321200_n.jpg?stp=dst-jpg_e35&efg=eyJ2ZW5jb2RlX3RhZyI6ImltYWdlX3VybGdlbi4xNDQweDE0NDAuc2RyIn0&_nc_ht=scontent.cdninstagram.com&_nc_cat=109&_nc_ohc=I3ub2tAql9MAX8afFTn&edm=APs17CUBAAAA&ccb=7-5&ig_cache_key=MzI2NjUwODM1MDI0NTY4ODg1NA%3D%3D.2-ccb7-5&oh=00_AfAEjuS6ZrHtgq_z-6Ng2Btq-SbLzuzeWWtXl3FF22J-dQ&oe=65EC29FB&_nc_sid=10d13b",
            "description": "Best Christmas ever \ud83e\udd70",
            "mentions": [],
            "likes": "560,863"
        }
    ]
}