{
    "username": "lucas_xx444",
    "profile_url": "https://www.instagram.com/lucas_xx444/",
    "followers": "12.1M",
    "following": "16",
    "number_of_posts": "158",
    "posts_info": [
        {
            "url": "https://www.instagram.com/p/C3zykKCPK_B/",
            "urlImage": "https://scontent.cdninstagram.com/v/t51.29350-15/429772424_794876052669174_2620728069475234052_n.jpg?stp=dst-jpg_e35&efg=eyJ2ZW5jb2RlX3RhZyI6ImltYWdlX3VybGdlbi4xNDQweDgxMC5zZHIifQ&_nc_ht=scontent.cdninstagram.com&_nc_cat=106&_nc_ohc=l5g9ragJ4PoAX-64D2O&edm=APs17CUBAAAA&ccb=7-5&ig_cache_key=MzMxMTIxMjUzODA0OTExNDA0OQ%3D%3D.2-ccb7-5&oh=00_AfDdCqOMsUixAsyWd-wXm3G_ifEyhFX8I_V5iAsN2J-g3w&oe=65EB6042&_nc_sid=10d13b",
            "description": "Photo by LUCAS on February 26, 2024. May be an image of 1 person, hair, top and text.",
            "mentions": [],
            "likes": "1,894,817"
        },
        {
            "url": "https://www.instagram.com/p/C3rzfMWvWzL/",
            "urlImage": "https://scontent.cdninstagram.com/v/t51.29350-15/392904230_1066725421075796_2394727742061931646_n.jpg?stp=dst-jpg_e35&efg=eyJ2ZW5jb2RlX3RhZyI6ImltYWdlX3VybGdlbi4xNDQweDE4MDAuc2RyIn0&_nc_ht=scontent.cdninstagram.com&_nc_cat=108&_nc_ohc=IDWe33qv5QYAX8RxeRF&edm=APs17CUBAAAA&ccb=7-5&ig_cache_key=MzMwODk2NDc5NTE3NjAyMTE5NQ%3D%3D.2-ccb7-5&oh=00_AfBEq0soEWV6lTuar1PZMkp1l0H8zB_Xtb50NcpRXYwXNw&oe=65EAE940&_nc_sid=10d13b",
            "description": "Photo shared by LUCAS on February 23, 2024 tagging @lucas_smofficial. May be an image of 1 person, hair, bolo tie and text.",
            "mentions": [
                "@lucas_smofficial."
            ],
            "likes": "3,066,739"
        },
        {
            "url": "https://www.instagram.com/p/C1bwAhpPcMB/",
            "urlImage": "https://scontent.cdninstagram.com/v/t51.29350-15/413893784_274224015313044_1052853865689559949_n.jpg?stp=dst-jpg_e35&efg=eyJ2ZW5jb2RlX3RhZyI6ImltYWdlX3VybGdlbi4xMzY3eDE1ODYuc2RyIn0&_nc_ht=scontent.cdninstagram.com&_nc_cat=100&_nc_ohc=CYcy7GowC04AX_4fFcU&edm=APs17CUBAAAA&ccb=7-5&ig_cache_key=MzI2ODQxNzA5Njk0NTM1MzQ3Mw%3D%3D.2-ccb7-5&oh=00_AfDtegRSDRYq5CM5Dsty7ilA7b9otxjbXTzV0DkW236gAw&oe=65EB7D6B&_nc_sid=10d13b",
            "description": "Photo by LUCAS on December 29, 2023. May be a closeup of one or more people and text.",
            "mentions": [],
            "likes": "2,564,236"
        },
        {
            "url": "https://www.instagram.com/p/CvvBe4khwRW/",
            "urlImage": "https://scontent.cdninstagram.com/v/t51.29350-15/366104084_815063066837140_7333776646765864634_n.jpg?stp=dst-jpg_e35&efg=eyJ2ZW5jb2RlX3RhZyI6ImltYWdlX3VybGdlbi4xMTIweDExMjAuc2RyIn0&_nc_ht=scontent.cdninstagram.com&_nc_cat=104&_nc_ohc=OCi7VF73G1YAX-QQ2GA&edm=APs17CUBAAAA&ccb=7-5&ig_cache_key=MzE2NTc1NTU4MzQzNzkzMTYwNg%3D%3D.2-ccb7-5&oh=00_AfBMbhhFSbyeNcE1DHQBI0WHvjFuIQ9jnTrVstMha65sxg&oe=65EB925C&_nc_sid=10d13b",
            "description": "Photo by LUCAS on August 09, 2023.",
            "mentions": [],
            "likes": "2,416,245"
        },
        {
            "url": "https://www.instagram.com/p/CsDVTYnP2Nx/",
            "urlImage": "https://scontent.cdninstagram.com/v/t51.29350-15/345981636_232861062687000_6194506006706413916_n.jpg?stp=dst-jpg_e35&efg=eyJ2ZW5jb2RlX3RhZyI6ImltYWdlX3VybGdlbi4xNDQweDE4MDAuc2RyIn0&_nc_ht=scontent.cdninstagram.com&_nc_cat=100&_nc_ohc=n6Z9YFjA7a0AX9mNyuV&edm=APs17CUBAAAA&ccb=7-5&ig_cache_key=MzA5OTQxNDY1OTYzNjA5MzgwOQ%3D%3D.2-ccb7-5&oh=00_AfDs3t3z-zRkM-1reIfbRNuX-0DRaApLD6P9qX8HXqs4RQ&oe=65EB9432&_nc_sid=10d13b",
            "description": "Photo by LUCAS on May 09, 2023.",
            "mentions": [],
            "likes": "3,515,001"
        },
        {
            "url": "https://www.instagram.com/p/CpMrqXHPP9q/",
            "urlImage": "https://scontent.cdninstagram.com/v/t51.29350-15/334074138_621963379772109_6720570103981990090_n.jpg?stp=dst-jpg_e35&efg=eyJ2ZW5jb2RlX3RhZyI6ImltYWdlX3VybGdlbi4xNDQweDE4MDAuc2RyIn0&_nc_ht=scontent.cdninstagram.com&_nc_cat=109&_nc_ohc=HmqKxJi5d2MAX81G7P3&edm=APs17CUBAAAA&ccb=7-5&ig_cache_key=MzA0ODAwMzA3MTA2Njg1NDA0MQ%3D%3D.2-ccb7-5&oh=00_AfCzZyuMwkawBrkBKXGhKmIXCj0m7qZH4_sgBh20U6XxHQ&oe=65EDEF7C&_nc_sid=10d13b",
            "description": "444",
            "mentions": [],
            "likes": "3,049,693"
        },
        {
            "url": "https://www.instagram.com/reel/CoHwVYnDtqv/",
            "urlImage": "https://scontent.cdninstagram.com/v/t51.2885-15/328309222_5640470286007394_4547348487152548474_n.jpg?stp=dst-jpg_e15&efg=eyJ2ZW5jb2RlX3RhZyI6ImltYWdlX3VybGdlbi4xMTc5eDIwOTYuc2RyIn0&_nc_ht=scontent.cdninstagram.com&_nc_cat=102&_nc_ohc=po8o5cK1qAUAX9qY2yp&edm=APs17CUBAAAA&ccb=7-5&ig_cache_key=MzAyODYwMTg1MDE5NjU4MTAzOQ%3D%3D.2-ccb7-5&oh=00_AfD2yOAlD5fAbGtICLll-MjaFiOrL2JKwltnej90jwrVdA&oe=65EADD19&_nc_sid=10d13b",
            "description": "",
            "mentions": [],
            "likes": "3,267,588"
        },
        {
            "url": "https://www.instagram.com/p/CnzZlTlL3CL/",
            "urlImage": "https://scontent.cdninstagram.com/v/t51.29350-15/327006304_1246974169576430_2621474576118079709_n.jpg?stp=dst-jpg_e35&efg=eyJ2ZW5jb2RlX3RhZyI6ImltYWdlX3VybGdlbi4xNDQweDE4MDAuc2RyIn0&_nc_ht=scontent.cdninstagram.com&_nc_cat=102&_nc_ohc=5fRDzY5bttsAX-cf2fx&edm=APs17CUBAAAA&ccb=7-5&ig_cache_key=MzAyMjg3MjI4MzMwMzYxNTk1MQ%3D%3D.2-ccb7-5&oh=00_AfCV83-dsAnIRlnulQwXaivHMPmRRSfe0W9pVJIlhLEa4Q&oe=65EC5A44&_nc_sid=10d13b",
            "description": "\ud83d\ude4f\ud83c\udffc",
            "mentions": [],
            "likes": "3,343,003"
        },
        {
            "url": "https://www.instagram.com/p/ChzS5nfhALF/",
            "urlImage": "https://scontent.cdninstagram.com/v/t51.29350-15/302046277_5447649301995762_5259906348855841343_n.jpg?stp=dst-jpg_e35&efg=eyJ2ZW5jb2RlX3RhZyI6ImltYWdlX3VybGdlbi4xNDQweDc1My5zZHIifQ&_nc_ht=scontent.cdninstagram.com&_nc_cat=106&_nc_ohc=rj7uJV0vkPQAX86GWoK&edm=APs17CUBAAAA&ccb=7-5&ig_cache_key=MjkxNDc1NjUwODA5MDg5Mjk5Nw%3D%3D.2-ccb7-5&oh=00_AfBP6wjAScWlPXa-N8xpd8rrrr9dg-ZbjiVlh2xxgKGa5A&oe=65EBD459&_nc_sid=10d13b",
            "description": "Photo by LUCAS on August 28, 2022.",
            "mentions": [],
            "likes": "3,945,226"
        },
        {
            "url": "https://www.instagram.com/p/CZwjwGqF60w/",
            "urlImage": "https://scontent.cdninstagram.com/v/t51.29350-15/273682707_899406850739429_2642468566036253828_n.jpg?stp=dst-jpg_e35&efg=eyJ2ZW5jb2RlX3RhZyI6ImltYWdlX3VybGdlbi4xMTY5eDExNjkuc2RyIn0&_nc_ht=scontent.cdninstagram.com&_nc_cat=105&_nc_ohc=zQKu97FL8oAAX9n9kQz&edm=APs17CUBAAAA&ccb=7-5&ig_cache_key=Mjc2OTg3MTAwODE0NDI3MjY4OA%3D%3D.2-ccb7-5&oh=00_AfDGeeXUJGyqpO1W_bdhPBkTJ2p1gnPWWR4eYjhAtn1a8Q&oe=65EADB4B&_nc_sid=10d13b",
            "description": "Photo by LUCAS on February 09, 2022.",
            "mentions": [],
            "likes": "4,647,364"
        },
        {
            "url": "https://www.instagram.com/p/CS_Q3qmBWOC/",
            "urlImage": "https://scontent.cdninstagram.com/v/t51.29350-15/240549362_531018294798381_5583729146650580168_n.jpg?stp=dst-jpg_e35&efg=eyJ2ZW5jb2RlX3RhZyI6ImltYWdlX3VybGdlbi4xNDEzeDE3Njcuc2RyIn0&_nc_ht=scontent.cdninstagram.com&_nc_cat=109&_nc_ohc=oJ142FBmWu0AX_q6e60&edm=APs17CUBAAAA&ccb=7-5&ig_cache_key=MjY0NzkwOTI5OTk2NzU4MzEwNg%3D%3D.2-ccb7-5&oh=00_AfDMprUJyzToyMTchhbEqGRBhsXKg2K899VEZCKg3Xj64Q&oe=65EAB635&_nc_sid=10d13b",
            "description": "Photo by LUCAS on August 25, 2021.",
            "mentions": [],
            "likes": "3,709,449"
        },
        {
            "url": "https://www.instagram.com/p/CS6WAlThQAd/",
            "urlImage": "https://scontent.cdninstagram.com/v/t51.29350-15/240449327_161968509390470_1393608023093270054_n.jpg?stp=dst-jpg_e35&efg=eyJ2ZW5jb2RlX3RhZyI6ImltYWdlX3VybGdlbi4xNDQweDk2MC5zZHIifQ&_nc_ht=scontent.cdninstagram.com&_nc_cat=102&_nc_ohc=dqKgT7h_A28AX8c0TAZ&edm=APs17CUBAAAA&ccb=7-5&ig_cache_key=MjY0NjUyNDUyODExMjc2MjkwOQ%3D%3D.2-ccb7-5&oh=00_AfDdmIQQHn90mISA9zoWC-v_0m6zO03QfSzcoEX6fcArfQ&oe=65EB34B4&_nc_sid=10d13b",
            "description": "Photo by LUCAS on August 23, 2021.",
            "mentions": [],
            "likes": "3,267,797"
        }
    ]
}