{
    "username": "paulolondra",
    "profile_url": "https://www.instagram.com/paulolondra/",
    "followers": "13.4M",
    "following": "378",
    "number_of_posts": "558",
    "posts_info": [
        {
            "url": "https://www.instagram.com/paulolondra/p/CluKh4aOSdP/",
            "urlImage": "https://scontent-bom1-2.cdninstagram.com/v/t51.29350-15/318134449_456184870040085_3310244926716982807_n.jpg?stp=dst-jpg_e35_s1080x1080&_nc_ht=scontent-bom1-2.cdninstagram.com&_nc_cat=109&_nc_ohc=zYuCUAuUM8QAX-6R2vT&edm=AOQ1c0wBAAAA&ccb=7-5&oh=00_AfBVSa-m6GphyCc3aRHL1FCjdRRsZgFdR451PiCuzsgQEA&oe=65EDD676&_nc_sid=8b3546",
            "description": "Photo shared by Paulo londra on December 03, 2022 tagging @leomessi.",
            "mentions": [
                "@leomessi."
            ],
            "likes": "4,974,587"
        },
        {
            "url": "https://www.instagram.com/paulolondra/p/C3oXV4Cu2Py/",
            "urlImage": "https://scontent-bom1-2.cdninstagram.com/v/t39.30808-6/408960334_18429487624013467_3759027210907296279_n.jpg?stp=dst-jpg_e35_s1080x1080_sh0.08&_nc_ht=scontent-bom1-2.cdninstagram.com&_nc_cat=107&_nc_ohc=pv-PVCfBF4cAX-UzxOb&edm=AOQ1c0wAAAAA&ccb=7-5&oh=00_AfCDqH4MS4ESD0tfN3B-MrblsmmtXEpuLW_oazdzfz78Sw&oe=65EDC45B&_nc_sid=8b3546",
            "description": "Photo by Paulo londra on February 21, 2024. May be an image of 2 people, baby, people smiling and people kissing.",
            "mentions": [],
            "likes": "1,111,224"
        },
        {
            "url": "https://www.instagram.com/paulolondra/p/C2lpoG5uliB/",
            "urlImage": "https://scontent-bom1-2.cdninstagram.com/v/t39.30808-6/422640987_18424829587013467_8782940432906723075_n.jpg?stp=dst-jpg_e35_p1080x1080_sh0.08&_nc_ht=scontent-bom1-2.cdninstagram.com&_nc_cat=107&_nc_ohc=v7KwnBrFlqoAX-f4z6P&edm=AOQ1c0wAAAAA&ccb=7-5&oh=00_AfDONelHnkt6qtHLTejzHSeIxdTHD94ZA3G1v-fSlBe7UQ&oe=65ED90F2&_nc_sid=8b3546",
            "description": "Photo by Paulo londra on January 26, 2024. May be an image of 1 person, hat, eyewear and text that says 'ORIGIA ORIGIALS ALS S ADIDAS 202 ------- 2020 \u122d\u12d8\u1265\u122d \u09a6\u0989\u09bf'.",
            "mentions": [],
            "likes": "628,944"
        },
        {
            "url": "https://www.instagram.com/paulolondra/p/C2LiGtHOvIu/",
            "urlImage": "https://scontent-bom1-2.cdninstagram.com/v/t39.30808-6/420156756_18422960035013467_3677754459541396270_n.jpg?stp=dst-jpg_e35_p1080x1080_sh0.08&_nc_ht=scontent-bom1-2.cdninstagram.com&_nc_cat=107&_nc_ohc=WRBr2j19wk0AX_oxZtN&edm=AOQ1c0wAAAAA&ccb=7-5&oh=00_AfCNgTGpYQLrikFkLkuDaiso1Cco0aFWjLTK6FoDhyEj5A&oe=65EE1741&_nc_sid=8b3546",
            "description": "Photo by Paulo londra on January 16, 2024. May be an image of 4 people, baby, kite, grass, picnic, park and text.",
            "mentions": [],
            "likes": "502,591"
        },
        {
            "url": "https://www.instagram.com/paulolondra/p/C0hz4cAO1ka/",
            "urlImage": "https://scontent-bom1-2.cdninstagram.com/v/t39.30808-6/406464384_18415005775013467_1818108411204353738_n.jpg?stp=dst-jpg_e35_s640x640_sh0.08&_nc_ht=scontent-bom1-2.cdninstagram.com&_nc_cat=107&_nc_ohc=NJyrpHHUmwIAX-8KWNz&edm=AOQ1c0wAAAAA&ccb=7-5&oh=00_AfD5Dh0Wg5WDM3yhFBNKMfAM13zRu91_bqCq4584mmbN3g&oe=65EE9777&_nc_sid=8b3546",
            "description": "Photo by Paulo londra on December 06, 2023.",
            "mentions": [],
            "likes": "629,824"
        },
        {
            "url": "https://www.instagram.com/paulolondra/p/C0SvjyzOg90/",
            "urlImage": "https://scontent-bom1-2.cdninstagram.com/v/t51.29350-15/405245339_261679819893657_6866614385122551111_n.jpg?stp=dst-jpg_e15&_nc_ht=scontent-bom1-2.cdninstagram.com&_nc_cat=109&_nc_ohc=L4ytUDJek54AX-fyIk-&edm=AOQ1c0wBAAAA&ccb=7-5&oh=00_AfDUAwOAM22PhbPnKzonSyKzxMw6lYgrMFRtjHNhH2bJ-Q&oe=65EACB97&_nc_sid=8b3546",
            "description": "Creo que lo tengo",
            "mentions": [],
            "likes": "492,486"
        },
        {
            "url": "https://www.instagram.com/paulolondra/p/Czd4XcDups7/",
            "urlImage": "https://scontent-bom1-2.cdninstagram.com/v/t39.30808-6/398976273_18409652452013467_2691537191348777927_n.jpg?stp=dst-jpg_e35_p1080x1080_sh0.08&_nc_ht=scontent-bom1-2.cdninstagram.com&_nc_cat=107&_nc_ohc=87ESnIj1FM4AX_V6WvN&edm=AOQ1c0wAAAAA&ccb=7-5&oh=00_AfAH9gc5YzG-UvbyrZ3KXm7pMCzmPpJbd78iYEovJlvxEQ&oe=65EEEAA8&_nc_sid=8b3546",
            "description": "Photo by Paulo londra on November 10, 2023.",
            "mentions": [],
            "likes": "477,913"
        },
        {
            "url": "https://www.instagram.com/paulolondra/p/CzEZVg_u6QU/",
            "urlImage": "https://scontent-bom1-2.cdninstagram.com/v/t39.30808-6/396265397_18407598175013467_5965371949849726514_n.jpg?stp=dst-jpg_e35_p1080x1080_sh0.08&_nc_ht=scontent-bom1-2.cdninstagram.com&_nc_cat=107&_nc_ohc=e5VwP65bTj4AX-8r4kA&edm=AOQ1c0wAAAAA&ccb=7-5&oh=00_AfCVQ0hYKcNzl3gMSiJl-0-s_zDtZe_NgukziS9y-nrz7A&oe=65EE6887&_nc_sid=8b3546",
            "description": "Photo by Paulo londra on October 31, 2023.",
            "mentions": [],
            "likes": "600,747"
        },
        {
            "url": "https://www.instagram.com/paulolondra/p/CyedLXIO6Dw/",
            "urlImage": "https://scontent-bom1-2.cdninstagram.com/v/t39.30808-6/393362482_18404771395013467_1680720494229543402_n.jpg?stp=dst-jpg_e35_s1080x1080_sh0.08&_nc_ht=scontent-bom1-2.cdninstagram.com&_nc_cat=107&_nc_ohc=VvMXGE8rVHwAX8IP1s6&edm=AOQ1c0wAAAAA&ccb=7-5&oh=00_AfBzQRljqM7PWuDWLqXVFZV_zRVfHrZYwIaBacksFHCjcA&oe=65ED67EB&_nc_sid=8b3546",
            "description": "Photo by Paulo londra on October 16, 2023.",
            "mentions": [],
            "likes": "542,805"
        },
        {
            "url": "https://www.instagram.com/paulolondra/p/CyYoJjeOS27/",
            "urlImage": "https://scontent-bom1-1.cdninstagram.com/v/t51.29350-15/403825493_363639686035367_2003168298840949842_n.jpg?stp=dst-jpg_e15&_nc_ht=scontent-bom1-1.cdninstagram.com&_nc_cat=111&_nc_ohc=jquvATv9UjIAX8kSYZ2&edm=AOQ1c0wBAAAA&ccb=7-5&oh=00_AfCEqp4r3DXWRQm-FBQ_zTVtP3g95OjVnX0Cdq-yx9Flaw&oe=65EAAC6B&_nc_sid=8b3546",
            "description": "Calentando motoresss\u2728 \n#DeTres\n#Creoquelotengo",
            "mentions": [],
            "likes": "739,157"
        },
        {
            "url": "https://www.instagram.com/paulolondra/p/CxtKgwsuTUh/",
            "urlImage": "https://scontent-bom1-2.cdninstagram.com/v/t39.30808-6/384396959_18401086483013467_5056682807138409184_n.jpg?stp=dst-jpg_e35_s1080x1080_sh0.08&_nc_ht=scontent-bom1-2.cdninstagram.com&_nc_cat=107&_nc_ohc=cDA9naijUiAAX8_4bib&edm=AOQ1c0wAAAAA&ccb=7-5&oh=00_AfCg_BOi1wgxgksA39MkNxbI1QWQ1hkllH3iS0uPUlLsIQ&oe=65ED923C&_nc_sid=8b3546",
            "description": "Photo by Paulo londra on September 27, 2023.",
            "mentions": [],
            "likes": "992,926"
        },
        {
            "url": "https://www.instagram.com/paulolondra/p/CxBtxf9OCuL/",
            "urlImage": "https://scontent-bom1-2.cdninstagram.com/v/t39.30808-6/375862585_18397865446013467_2413356042010499274_n.jpg?stp=dst-jpg_e35_p1080x1080_sh0.08&_nc_ht=scontent-bom1-2.cdninstagram.com&_nc_cat=107&_nc_ohc=lmq_UlpR7u4AX98KNJd&edm=AOQ1c0wAAAAA&ccb=7-5&oh=00_AfBO_H3meWeez99URSAIPyBzK1qSQG9I0X7WPEjowLIScg&oe=65EE74B3&_nc_sid=8b3546",
            "description": "Photo by Paulo londra on September 10, 2023.",
            "mentions": [],
            "likes": "1,114,710"
        }
    ]
}